setup.cfg
setup.py
pubnub_blocks_client/__init__.py
pubnub_blocks_client/endpoints.py
pubnub_blocks_client/exceptions.py
pubnub_blocks_client/utils.py
pubnub_blocks_client.egg-info/PKG-INFO
pubnub_blocks_client.egg-info/SOURCES.txt
pubnub_blocks_client.egg-info/dependency_links.txt
pubnub_blocks_client.egg-info/not-zip-safe
pubnub_blocks_client.egg-info/requires.txt
pubnub_blocks_client.egg-info/top_level.txt
pubnub_blocks_client/core/__init__.py
pubnub_blocks_client/core/api.py
pubnub_blocks_client/models/__init__.py
pubnub_blocks_client/models/account.py
pubnub_blocks_client/models/api_access.py
pubnub_blocks_client/models/application.py
pubnub_blocks_client/models/block.py
pubnub_blocks_client/models/event_handler.py
pubnub_blocks_client/models/keyset.py
pubnub_blocks_client/models/model.py
pubnub_blocks_client/models/owner.py
pubnub_blocks_client/models/user.py