Metadata-Version: 1.1
Name: pubnub-blocks-client
Version: 1.1.0
Summary: PubNub BLOCKS management.
Home-page: http://pubnub.com
Author: PubNub
Author-email: support@pubnub.com
License: MIT
Download-URL: https://github.com/pubnub/pubnub-blocks-client/tarball/1.1.0
Keywords: pubnub,blocks,event handlers,manage
Platform: UNKNOWN
Classifier: Development Status :: 5 - Production/Stable
Classifier: Environment :: Console
Classifier: Intended Audience :: Developers
Classifier: Intended Audience :: Information Technology
Classifier: Intended Audience :: System Administrators
Classifier: License :: OSI Approved :: GNU General Public License v3 or later (GPLv3+)
Classifier: Natural Language :: English
Classifier: Operating System :: POSIX
Classifier: Programming Language :: Python :: 2.7
Classifier: Programming Language :: Python :: 3
Classifier: Topic :: System :: Installation/Setup
Classifier: Topic :: System :: Systems Administration
Classifier: Topic :: Utilities
